gsmu/__init__.py
gsmu/core.py
gsmu/main.py
git_submodule_updater-0.0.1.dist-info/METADATA
git_submodule_updater-0.0.1.dist-info/WHEEL
git_submodule_updater-0.0.1.dist-info/entry_points.txt
git_submodule_updater-0.0.1.dist-info/top_level.txt
git_submodule_updater-0.0.1.dist-info/RECORD
