Metadata-Version: 2.1
Name: git-submodule-updater
Version: 0.0.1
Summary: Lemme make a PR for you to update that git submodule
Home-page: https://github.com/peterbe/git-submodule-updater
Author: Peter Bengtsson
Author-email: mail@peterbe.com
License: MPL 2.0
Keywords: git github submodule
Platform: UNKNOWN
Classifier: Programming Language :: Python
Classifier: Programming Language :: Python :: 3
Classifier: Programming Language :: Python :: Implementation :: CPython
Classifier: License :: OSI Approved :: Mozilla Public License 2.0 (MPL 2.0)
Requires-Dist: GitPython
Requires-Dist: click
Requires-Dist: PyGithub
Requires-Dist: python-decouple
